fastango_v1/__init__.py
fastango_v1/app.py
fastango_v1/middleware.py
fastango_v1/response.py
fastango_v1-0.1.7.dist-info/METADATA
fastango_v1-0.1.7.dist-info/WHEEL
fastango_v1-0.1.7.dist-info/top_level.txt
fastango_v1-0.1.7.dist-info/RECORD
