Metadata-Version: 2.1
Name: fastango-v1
Version: 0.1.7
Summary: Python Web Framework build for learning purposes
Home-page: https://github.com/me/myproject
Author: Mirmux
Author-email: mirfayziyev5@gmail.com
License: MIT
Platform: UNKNOWN
Classifier: License :: OSI Approved :: MIT License
Classifier: Programming Language :: Python
Classifier: Programming Language :: Python :: 3
Classifier: Programming Language :: Python :: 3.6
Classifier: Programming Language :: Python :: Implementation :: CPython
Classifier: Programming Language :: Python :: Implementation :: PyPy
Requires-Python: >=3.8.0
Requires-Dist: Jinja2 (==3.1.4)
Requires-Dist: parse (==1.20.2)
Requires-Dist: requests (==2.32.3)
Requires-Dist: requests-wsgi-adapter (==0.4.1)
Requires-Dist: WebOb (==1.8.7)
Requires-Dist: whitenoise (==6.7.0)
Requires-Dist: gunicorn (==22.0.0)
